kgapitest/__init__.py
kgapitest/apis.py
kgapitest-0.1.0.dist-info/METADATA
kgapitest-0.1.0.dist-info/WHEEL
kgapitest-0.1.0.dist-info/RECORD
