Metadata-Version: 2.1
Name: kgapitest
Version: 0.1.0
Summary: 
Author: Farid Seifi
Author-email: faridsei@med.umich.edu
Requires-Python: >=3.10,<4.0
Classifier: Programming Language :: Python :: 3
Classifier: Programming Language :: Python :: 3.10
Classifier: Programming Language :: Python :: 3.11
Requires-Dist: fastapi (>=0.97.0,<0.98.0)
